{"total":176,"pageSize":10,"pageCount":18,"data":[{"title":"DeepMAG-使用多智能体图进行深度强化学习以实现灵活的作业车间调度","slug":"DeepMAG-使用多智能体图进行深度强化学习以实现灵活的作业车间调度","date":"2023-05-31T09:20:59.000Z","updated":"2023-05-31T09:34:09.569Z","comments":true,"path":"api/articles/DeepMAG-使用多智能体图进行深度强化学习以实现灵活的作业车间调度.json","excerpt":null,"keywords":null,"cover":"http://cdn.leafii.top/img/image-20230525205309249.png","content":null,"raw":null,"categories":[],"tags":[{"name":"知识图谱","path":"api/tags/知识图谱.json"},{"name":"车间调度","path":"api/tags/车间调度.json"}]},{"title":"leetcode98.验证二叉搜索树","slug":"leetcode98-验证二叉搜索树","date":"2023-05-31T06:11:21.000Z","updated":"2023-05-31T06:28:58.366Z","comments":true,"path":"api/articles/leetcode98-验证二叉搜索树.json","excerpt":null,"keywords":null,"cover":"http://cdn.leafii.top/img/tree1-20230531141156695.jpg","content":null,"raw":null,"categories":[],"tags":[{"name":"leetcode","path":"api/tags/leetcode.json"},{"name":"算法","path":"api/tags/算法.json"},{"name":"二叉树","path":"api/tags/二叉树.json"}]},{"title":"leetcode617.合并二叉树","slug":"leetcode617-合并二叉树","date":"2023-05-29T23:49:07.000Z","updated":"2023-05-29T23:55:24.400Z","comments":true,"path":"api/articles/leetcode617-合并二叉树.json","excerpt":null,"keywords":null,"cover":"http://cdn.leafii.top/img/merge.jpg","content":null,"raw":null,"categories":[],"tags":[{"name":"leetcode","path":"api/tags/leetcode.json"},{"name":"算法","path":"api/tags/算法.json"},{"name":"二叉树","path":"api/tags/二叉树.json"}]},{"title":"leetcode700.二叉搜索树中的搜索","slug":"leetcode700-二叉搜索树中的搜索","date":"2023-05-29T07:09:15.000Z","updated":"2023-05-29T07:13:35.122Z","comments":true,"path":"api/articles/leetcode700-二叉搜索树中的搜索.json","excerpt":null,"keywords":null,"cover":"http://cdn.leafii.top/img/tree1.jpg","content":null,"raw":null,"categories":[],"tags":[{"name":"leetcode","path":"api/tags/leetcode.json"},{"name":"算法","path":"api/tags/算法.json"},{"name":"二叉树","path":"api/tags/二叉树.json"}]},{"title":"leetcode188.买卖股票的最佳时机IV","slug":"leetcode188-买卖股票的最佳时机IV","date":"2023-05-24T08:54:22.000Z","updated":"2023-05-24T08:54:54.618Z","comments":true,"path":"api/articles/leetcode188-买卖股票的最佳时机IV.json","excerpt":null,"keywords":null,"cover":null,"content":null,"raw":null,"categories":[],"tags":[{"name":"leetcode","path":"api/tags/leetcode.json"},{"name":"算法","path":"api/tags/算法.json"},{"name":"动态规划","path":"api/tags/动态规划.json"}]},{"title":"leetcode518.零钱兑换II","slug":"leetcode518-零钱兑换II","date":"2023-05-23T11:02:09.000Z","updated":"2023-05-23T11:04:16.584Z","comments":true,"path":"api/articles/leetcode518-零钱兑换II.json","excerpt":null,"keywords":null,"cover":null,"content":null,"raw":null,"categories":[],"tags":[{"name":"leetcode","path":"api/tags/leetcode.json"},{"name":"算法","path":"api/tags/算法.json"},{"name":"动态规划","path":"api/tags/动态规划.json"}]},{"title":"leetcode322.零钱兑换","slug":"leetcode322-零钱兑换","date":"2023-05-22T08:09:17.000Z","updated":"2023-05-22T08:11:34.895Z","comments":true,"path":"api/articles/leetcode322-零钱兑换.json","excerpt":null,"keywords":null,"cover":null,"content":null,"raw":null,"categories":[],"tags":[{"name":"leetcode","path":"api/tags/leetcode.json"},{"name":"算法","path":"api/tags/算法.json"},{"name":"动态规划","path":"api/tags/动态规划.json"}]},{"title":"leetcode1207.独一无二的出现次数","slug":"leetcode1207-独一无二的出现次数","date":"2023-05-21T07:23:35.000Z","updated":"2023-05-21T07:26:06.451Z","comments":true,"path":"api/articles/leetcode1207-独一无二的出现次数.json","excerpt":null,"keywords":null,"cover":null,"content":null,"raw":null,"categories":[],"tags":[{"name":"leetcode","path":"api/tags/leetcode.json"},{"name":"算法","path":"api/tags/算法.json"}]},{"title":"leetcode1365.有多少小于当前数字的数字","slug":"leetcode1365-有多少小于当前数字的数字","date":"2023-05-20T08:16:48.000Z","updated":"2023-05-20T08:53:08.938Z","comments":true,"path":"api/articles/leetcode1365-有多少小于当前数字的数字.json","excerpt":null,"keywords":null,"cover":null,"content":null,"raw":null,"categories":[],"tags":[{"name":"leetcode","path":"api/tags/leetcode.json"},{"name":"算法","path":"api/tags/算法.json"}]},{"title":"leetcode906.超级回文数","slug":"leetcode906-超级回文数","date":"2023-05-19T09:43:18.000Z","updated":"2023-05-19T09:45:56.607Z","comments":true,"path":"api/articles/leetcode906-超级回文数.json","excerpt":null,"keywords":null,"cover":null,"content":null,"raw":null,"categories":[],"tags":[{"name":"leetcode","path":"api/tags/leetcode.json"},{"name":"算法","path":"api/tags/算法.json"}]}]}